deflector/__init__.py
deflector/cli/main.py
deflector/config/each.py
deflector/config/identation.py
deflector/helpers/after_each.py
deflector/helpers/before_each.py
deflector/helpers/describe.py
deflector/helpers/it.py
deflector/models/affirm/__init__.py
deflector/models/assertion/__init__.py
deflector/models/assertion/assertion_error.py
deflector/models/each.py
deflector/modules/__init__.py
deflector/modules/essentials/__init__.py
deflector/modules/essentials/affirm.py
deflector/services/__init__.py
deflector/services/affirm.py
deflector/utils/colors.py
deflector/utils/errors.py
deflector/utils/execute_function.py
deflector-0.1.1.dist-info/LICENSE
deflector-0.1.1.dist-info/METADATA
deflector-0.1.1.dist-info/WHEEL
deflector-0.1.1.dist-info/entry_points.txt
deflector-0.1.1.dist-info/RECORD
