Metadata-Version: 2.1
Name: deflector
Version: 0.1.1
Summary: Deflector is a minimalist testing library for Python designed to simplify test writing with a clear and intuitive syntax, allowing developers to create and run tests quickly and efficiently without unnecessary complications.
Home-page: https://github.com/richecr/deflector
License: LICENSE
Keywords: test,ent-2-end,unit tests,assert,equal,ensure,affirm,validation,python
Author: Rich Ramalho
Author-email: richecr1799@gmail.com
Maintainer: Rich Ramalho
Maintainer-email: richecr1799@gmail.com
Requires-Python: >=3.12,<4.0
Classifier: License :: Other/Proprietary License
Classifier: Programming Language :: Python :: 3
Classifier: Programming Language :: Python :: 3.12
Requires-Dist: rich (>=13.7.1,<14.0.0)
Requires-Dist: typer (>=0.12.3,<0.13.0)
Project-URL: Documentation, https://github.com/richecr/deflector
Project-URL: Repository, https://github.com/richecr/deflector
